mkite_db/manage.py
mkite_db/cfg/__init__.py
mkite_db/cfg/asgi.py
mkite_db/cfg/settings.py
mkite_db/cfg/urls.py
mkite_db/cfg/wsgi.py
mkite_db/cli/run_manage.py
mkite_db/dbimport/__init__.py
mkite_db/dbimport/asefile.py
mkite_db/dbimport/base.py
mkite_db/dbimport/infofile.py
mkite_db/dbimport/molfile.py
mkite_db/dbimport/mp.py
mkite_db/dbimport/pmgfile.py
mkite_db/dbimport/tests/__init__.py
mkite_db/dbimport/tests/test_asefile.py
mkite_db/dbimport/tests/test_infofile.py
mkite_db/dbimport/tests/test_molfile.py
mkite_db/dbimport/tests/test_mp.py
mkite_db/dbimport/tests/test_pmgfile.py
mkite_db/orm/.gitignore
mkite_db/orm/__init__.py
mkite_db/orm/deserializers.py
mkite_db/orm/models.py
mkite_db/orm/repr.py
mkite_db/orm/serializers.py
mkite_db/orm/base/__init__.py
mkite_db/orm/base/apps.py
mkite_db/orm/base/models.py
mkite_db/orm/base/serializers.py
mkite_db/orm/base/tests/__init__.py
mkite_db/orm/base/tests/test_models.py
mkite_db/orm/base/tests/test_serializers.py
mkite_db/orm/jobs/__init__.py
mkite_db/orm/jobs/apps.py
mkite_db/orm/jobs/deleter.py
mkite_db/orm/jobs/models.py
mkite_db/orm/jobs/serializers.py
mkite_db/orm/jobs/management/commands/__init__.py
mkite_db/orm/jobs/management/commands/create_experiment.py
mkite_db/orm/jobs/management/commands/create_project.py
mkite_db/orm/jobs/management/commands/scanrecipes.py
mkite_db/orm/jobs/management/commands/summarize_jobs.py
mkite_db/orm/jobs/management/commands/tests/__init__.py
mkite_db/orm/jobs/management/commands/tests/test_scanrecipes.py
mkite_db/orm/jobs/tests/__init__.py
mkite_db/orm/jobs/tests/test_deleter.py
mkite_db/orm/jobs/tests/test_models.py
mkite_db/orm/jobs/tests/test_serializers.py
mkite_db/orm/mols/__init__.py
mkite_db/orm/mols/apps.py
mkite_db/orm/mols/models.py
mkite_db/orm/mols/serializers.py
mkite_db/orm/mols/tests/__init__.py
mkite_db/orm/mols/tests/test_models.py
mkite_db/orm/mols/tests/test_serializers.py
mkite_db/orm/structs/__init__.py
mkite_db/orm/structs/apps.py
mkite_db-25.11.3.dist-info/licenses/LICENSE
mkite_db-25.11.3.dist-info/licenses/NOTICE
mkite_db-25.11.3.dist-info/METADATA
mkite_db-25.11.3.dist-info/WHEEL
mkite_db-25.11.3.dist-info/entry_points.txt
mkite_db-25.11.3.dist-info/top_level.txt
mkite_db-25.11.3.dist-info/RECORD
