Metadata-Version: 2.4
Name: mkite_db
Version: 25.11.3
Summary: mkite: distributed computing platform for high-throughput materials simulations
Author-email: Daniel Schwalbe-Koda <dskoda@ucla.edu>
Keywords: workflow,materials-science
Requires-Python: >=3.8
License-File: LICENSE
License-File: NOTICE
Requires-Dist: Django>=4.2
Requires-Dist: django-taggit
Requires-Dist: django-environ
Requires-Dist: django-filter
Requires-Dist: django-extensions>=3.2.1
Requires-Dist: django-coverage
Requires-Dist: djangorestframework>=3.14.0
Requires-Dist: psycopg>=3.1.8
Requires-Dist: model_bakery
Requires-Dist: msgspec>=0.14.1
Requires-Dist: click
Requires-Dist: pydantic>=2.0
Requires-Dist: ase
Requires-Dist: pymatgen
Requires-Dist: mp_api
Requires-Dist: mkite_core
Requires-Dist: mkite_engines
Dynamic: license-file
